pytket/extensions/braket/__init__.py
pytket/extensions/braket/_metadata.py
pytket/extensions/braket/braket_convert.py
pytket/extensions/braket/py.typed
pytket/extensions/braket/backends/__init__.py
pytket/extensions/braket/backends/braket.py
pytket/extensions/braket/backends/config.py
pytket_braket-0.46.0.dist-info/licenses/LICENSE
tests/backend_test.py
tests/conftest.py
tests/convert_test.py
pytket_braket-0.46.0.dist-info/METADATA
pytket_braket-0.46.0.dist-info/WHEEL
pytket_braket-0.46.0.dist-info/top_level.txt
pytket_braket-0.46.0.dist-info/RECORD
