Metadata-Version: 2.4
Name: pytket-braket
Version: 0.46.0
Summary: Extension for pytket, providing access to Amazon Braket backends
Author-email: TKET development team <tket-support@quantinuum.com>
Maintainer-email: TKET development team <tket-support@quantinuum.com>
License:                                  Apache License
Project-URL: documentation, https://tket.quantinuum.com/extensions/pytket-braket/index.html
Project-URL: source, https://github.com/Quantinuum/pytket-braket
Project-URL: tracker, https://github.com/Quantinuum/pytket-braket/issues
Classifier: Environment :: Console
Classifier: Programming Language :: Python :: 3.10
Classifier: Programming Language :: Python :: 3.11
Classifier: Programming Language :: Python :: 3.12
Classifier: Programming Language :: Python :: 3.13
Classifier: Operating System :: MacOS :: MacOS X
Classifier: Operating System :: POSIX :: Linux
Classifier: Operating System :: Microsoft :: Windows
Classifier: Intended Audience :: Developers
Classifier: Intended Audience :: Science/Research
Classifier: Topic :: Scientific/Engineering
Requires-Python: <4.0,>=3.10
License-File: LICENSE
Requires-Dist: pytket>=2.11.0
Requires-Dist: amazon-braket-sdk~=1.101
Requires-Dist: amazon-braket-schemas~=1.26
Requires-Dist: amazon-braket-default-simulator~=1.29
Requires-Dist: boto3-stubs
Requires-Dist: llvmlite>=0.37.0
Requires-Dist: numba>=0.48.0
Dynamic: license-file
